mkgist/__init__.py
mkgist-3.5.data/scripts/mkgist
mkgist-3.5.dist-info/LICENSE
mkgist-3.5.dist-info/METADATA
mkgist-3.5.dist-info/WHEEL
mkgist-3.5.dist-info/top_level.txt
mkgist-3.5.dist-info/RECORD
