Metadata-Version: 2.1
Name: mkgist
Version: 3.5
Summary: A small utility for making gists
Home-page: https://github.com/mtn/mkgist
Author: Michael Noronha
Author-email: michaeltnoronha@gmail.com
License: MIT
Platform: UNKNOWN
Classifier: Programming Language :: Python :: 3
Classifier: License :: OSI Approved :: MIT License
Classifier: Operating System :: OS Independent
Requires-Dist: certifi (==2019.3.9)
Requires-Dist: chardet (==3.0.4)
Requires-Dist: idna (==2.8)
Requires-Dist: pyperclip (==1.7.0)
Requires-Dist: requests (==2.21.0)
Requires-Dist: urllib3 (==1.24.1)
